otree_survey/__init__.py
otree_survey/bots.py
otree_survey/browser_info.py
otree_survey/fields.py
otree_survey/pages.py
otree_survey/prolific.py
otree_survey/urls.py
otree_survey/utils.py
otree_survey/views.py
otree_survey/widgets.py
otree_survey/errors/email.py
otree_survey/errors/settings.py
otree_survey/errors/utils.py
otree_survey/errors/views.py
otree_survey/locale/de/LC_MESSAGES/django.po
otree_survey/locale/fr/LC_MESSAGES/django.po
otree_survey/management/commands/export_pos.py
otree_survey/management/commands/generate_data.py
otree_survey/management/commands/import_pos.py
otree_survey/participant/views.py
otree_survey/static/css/slider.css
otree_survey/static/jquery-ui/jquery.ui.labeledslider.css
otree_survey/static/jquery-ui/jquery.ui.labeledslider.js
otree_survey/static/js/slider.js
otree_survey/static/otree_survey/otree_survey.css
otree_survey/templates/otree_survey/LikertScale.html
otree_survey/templates/otree_survey/SurveyPage.html
otree_survey/templates/otree_survey/robots.txt
otree_survey/templates/otree_survey/includes/browser_info.html
otree_survey/templates/otree_survey/tags/BackButton.html
otree_survey/templates/otree_survey/tags/Formfield.html
otree_survey/templates/otree_survey/tags/FormfieldOnly.html
otree_survey/templates/otree_survey/tags/LikertFields.html
otree_survey/templates/otree_survey/tags/NavigationButtons.html
otree_survey/templates/otree_survey/tags/ProgressBar.html
otree_survey/templates/otree_survey/widgets/tickslider.html
otree_survey/templatetags/otree_survey.py
otree_survey-0.2.8.dist-info/WHEEL
otree_survey-0.2.8.dist-info/METADATA
otree_survey-0.2.8.dist-info/RECORD
