Metadata-Version: 2.1
Name: otree_survey
Version: 0.2.8
Summary: Design surveys in oTree
Home-page: https://github.com/csemken/otree-survey/
Author: Christoph Semken
Author-email: otree.dev@csemken.eu
Requires-Python: >=3.7
Classifier: License :: OSI Approved :: GNU General Public License v3 or later (GPLv3+)
Requires-Dist: otree>=3.3,<5
Requires-Dist: pre-commit ; extra == "dev"
Requires-Dist: keyring ; extra == "dev"
Requires-Dist: sphinx ; extra == "doc"
Requires-Dist: myst-parser ; extra == "doc"
Requires-Dist: nbsphinx ; extra == "doc"
Requires-Dist: sphinx-rtd-theme ; extra == "doc"
Provides-Extra: dev
Provides-Extra: doc
